horizons/__init__.py
horizons/__main__.py
horizons/core.py
horizons/parse_table.py
horizons-0.2.2.dist-info/LICENSE
horizons-0.2.2.dist-info/METADATA
horizons-0.2.2.dist-info/WHEEL
horizons-0.2.2.dist-info/top_level.txt
horizons-0.2.2.dist-info/RECORD
