Metadata-Version: 2.1
Name: horizons
Version: 0.2.2
Summary: JPL HORIZONS System client
Home-page: UNKNOWN
Author: David Dupre
License: MIT License
Platform: UNKNOWN
Classifier: Programming Language :: Python :: 3
Classifier: Programming Language :: Python :: 3 :: Only
Classifier: License :: OSI Approved :: MIT License
Classifier: Operating System :: OS Independent
Classifier: Topic :: Scientific/Engineering :: Astronomy
Classifier: Development Status :: 3 - Alpha
